{
  "id": 1348,
  "attributes": {
    "name": "Микуленко Максим",
    "number": "+380660097190",
    "eMail": "maks7294@gmail.com",
    "age": "30",
    "englishLevel": "intermediate",
    "createdAt": "2024-06-18T07:43:35.034Z",
    "updatedAt": "2024-06-18T07:43:35.034Z",
    "publishedAt": "2024-06-18T07:43:35.027Z",
    "locale": "ru",
    "Checked": false,
    "pageFrom": "https://ua.rem-s.com/developers/front-end-developer",
    "cv_link": "",
    "CV_url": "/uploads/CV_Maksym_Mykulenko_FE_f91cfd0bb8.pdf"
  }
}