{
  "id": 1533,
  "attributes": {
    "name": "Marcoci Denis",
    "number": "+40758953633",
    "eMail": "dmarcoci00@gmail.com",
    "age": "22",
    "englishLevel": "advanced",
    "createdAt": "2024-10-14T14:51:05.351Z",
    "updatedAt": "2024-10-14T14:51:05.351Z",
    "publishedAt": "2024-10-14T14:51:05.342Z",
    "locale": "ru",
    "Checked": false,
    "pageFrom": "https://rem-s.com/developers/front-end-developer",
    "cv_link": "",
    "CV_url": "/uploads/Denis_Marcoci_Resume_4df078865e.pdf"
  }
}