{
  "id": 1798,
  "attributes": {
    "name": "Mark Klymovskyy",
    "number": "+380968571251",
    "eMail": "mklymovskyy@gmail.com",
    "age": null,
    "englishLevel": "advanced",
    "createdAt": "2025-04-07T11:05:20.397Z",
    "updatedAt": "2025-06-03T14:51:10.118Z",
    "publishedAt": "2025-04-07T11:05:20.390Z",
    "locale": "ru",
    "Checked": true,
    "pageFrom": "https://ua.rem-s.com/tutors/project-management-tutor",
    "cv_link": "",
    "CV_url": "/uploads/CV_Mark_Klymovskyi_Senior_Project_Manager_a1d2ffe983.pdf"
  }
}