{
  "id": 197,
  "attributes": {
    "name": "Alla Urban",
    "number": "+380682042085",
    "eMail": "alurmah@gmail.com",
    "age": "32",
    "englishLevel": "intermediate",
    "createdAt": "2023-04-03T12:46:39.036Z",
    "updatedAt": "2023-04-03T12:46:39.036Z",
    "publishedAt": "2023-04-03T12:46:39.022Z",
    "locale": "ru",
    "Checked": false,
    "pageFrom": "https://rem-s.com/design/artist-illustrator",
    "cv_link": "",
    "CV_url": "/uploads/Rezyume_Illyustrator_dizajner_hudozhnik_prepodavatel_Illustrator_Photoshop_Alla_Urban_2e7b915e3b.docx"
  }
}