{
  "id": 212,
  "attributes": {
    "name": "Лихопол Єва Романівна",
    "number": "+380637673786",
    "eMail": "yeva.lykhopol.ux@gmail.com",
    "age": "20",
    "englishLevel": "upper-intermediate",
    "createdAt": "2023-04-06T10:26:37.036Z",
    "updatedAt": "2023-04-06T10:26:37.036Z",
    "publishedAt": "2023-04-06T10:26:37.019Z",
    "locale": "ru",
    "Checked": false,
    "pageFrom": "https://rem-s.com/ua/design/ui-ux-designer",
    "cv_link": "",
    "CV_url": "/uploads/Yeva_Lykhopol_UX_UI_CV_ce437177df.pdf"
  }
}