{
  "id": 2854,
  "attributes": {
    "name": "Noel Christ Anne Bianca",
    "number": "+50938770177",
    "eMail": "noelbianca2006@gmail.com",
    "age": null,
    "englishLevel": "advanced",
    "createdAt": "2025-11-22T18:37:11.569Z",
    "updatedAt": "2025-11-22T18:37:11.569Z",
    "publishedAt": "2025-11-22T18:37:11.556Z",
    "locale": "ru",
    "Checked": false,
    "pageFrom": "https://rem-s.com/en/managers/chat-operator",
    "cv_link": "",
    "CV_url": "/uploads/Noel_Christ_Anne_Bianca_Resume_CV_pdf_97dd53631a.docx"
  }
}