{
  "id": 650,
  "attributes": {
    "name": "Калабішка Кароліна Романівна",
    "number": "+380665371929",
    "eMail": "kalabishkalina991@gmail.com",
    "age": "23",
    "englishLevel": "pre-intermediate",
    "createdAt": "2023-07-04T16:39:15.022Z",
    "updatedAt": "2023-07-04T16:39:15.022Z",
    "publishedAt": "2023-07-04T16:39:15.003Z",
    "locale": "ru",
    "Checked": false,
    "pageFrom": "https://rem-s.com/ua/designers/ui-ux-designer",
    "cv_link": "",
    "CV_url": "/uploads/Kalabishka_Karolina_CV_1_f8187f1249.pdf"
  }
}