{
  "id": 716,
  "attributes": {
    "name": "Олександр",
    "number": "+380987743778",
    "eMail": "favorstreet21@gmail.com",
    "age": "47",
    "englishLevel": "beginner",
    "createdAt": "2023-07-15T11:06:23.218Z",
    "updatedAt": "2023-07-15T11:06:23.218Z",
    "publishedAt": "2023-07-15T11:06:23.193Z",
    "locale": "ru",
    "Checked": false,
    "pageFrom": "https://rem-s.com/ua/about",
    "cv_link": "https://resume.io/r/LKcP1hfRI",
    "CV_url": "/uploads/oleksandr_borymskyi_resume_web_dev_dcf19369dd.pdf"
  }
}