{
  "id": 928,
  "attributes": {
    "name": "Голько Віталій",
    "number": "+380638415853",
    "eMail": "impro9712@gmail.com",
    "age": "26",
    "englishLevel": "intermediate",
    "createdAt": "2023-09-20T13:11:31.519Z",
    "updatedAt": "2023-09-20T13:11:31.519Z",
    "publishedAt": "2023-09-20T13:11:31.504Z",
    "locale": "ru",
    "Checked": false,
    "pageFrom": "https://rem-s.com/ua",
    "cv_link": "https://drive.google.com/file/d/1-fdAE_fM4myQZJXjsTqf1hyjG1_IzHML/view?usp=sharing",
    "CV_url": "/uploads/Holko_CV_eng_013b95fbea.pdf"
  }
}