{
  "id": 1078,
  "attributes": {
    "name": "Kashyrets Ivanna ",
    "number": "+380969875235",
    "eMail": "kasirecivanna@gmail.com",
    "age": "20",
    "englishLevel": "advanced",
    "createdAt": "2024-01-03T13:34:28.575Z",
    "updatedAt": "2024-01-03T13:34:28.575Z",
    "publishedAt": "2024-01-03T13:34:28.557Z",
    "locale": "ru",
    "Checked": false,
    "pageFrom": "https://ua.rem-s.com/developers/full-stack-developer",
    "cv_link": "",
    "CV_url": "/uploads/Full_Stack_Kashyrets_96b5ebf20f.pdf"
  }
}