{
  "id": 490,
  "attributes": {
    "name": "Zenon Savchenko",
    "number": "+380500888785",
    "eMail": "zenon.savch@gmail.com",
    "age": "20",
    "englishLevel": "intermediate",
    "createdAt": "2023-05-19T13:24:47.271Z",
    "updatedAt": "2023-05-19T13:24:47.271Z",
    "publishedAt": "2023-05-19T13:24:47.256Z",
    "locale": "ru",
    "Checked": false,
    "pageFrom": "https://rem-s.com/ua/developers/python-developer",
    "cv_link": "",
    "CV_url": "/uploads/CV_Zenon_Savchenko_Python_Developer_6371a22253.pdf"
  }
}