{
  "id": 722,
  "attributes": {
    "name": "Іванчо Микола",
    "number": "+380934865352",
    "eMail": "nick.ivancho@gmail.com",
    "age": "35",
    "englishLevel": "upper-intermediate",
    "createdAt": "2023-07-19T05:56:10.707Z",
    "updatedAt": "2023-07-19T05:56:10.707Z",
    "publishedAt": "2023-07-19T05:56:10.692Z",
    "locale": "ru",
    "Checked": false,
    "pageFrom": "https://rem-s.com/ua/designers/ui-ux-designer",
    "cv_link": "",
    "CV_url": "/uploads/CV_nick_vancho_6094df8e90.pdf"
  }
}